dicom_tools/__init__.py
dicom_tools/exporter.py
dicom_tools/mapping.py
dicom_tools/parser.py
dicom_tools/scanner.py
dicom_tools/types.py
dicom_tools/utils.py
src/__init__.py
src/api/__init__.py
src/api/dicom_api.py
src/api/metadata_api.py
src/api/query_api.py
src/core/__init__.py
src/core/series_processor.py
src/core/uploader.py
src/models/__init__.py
src/models/dicom_models.py
src/utils/__init__.py
src/utils/config_loader.py
src/utils/progress.py
getcookie.py
getcrpit.py
main.py
smart_analyzer.py
upload.py
dicom_tools_mcp_test-1.0.2.dist-info/METADATA
dicom_tools_mcp_test-1.0.2.dist-info/WHEEL
dicom_tools_mcp_test-1.0.2.dist-info/entry_points.txt
dicom_tools_mcp_test-1.0.2.dist-info/licenses/LICENSE
dicom_tools_mcp_test-1.0.2.dist-info/RECORD
