Metadata-Version: 2.4
Name: dicom-tools-mcp-test
Version: 1.0.2
Summary: 基于 MCP (Model Context Protocol) 的 DICOM 医学影像文件分析工具
Project-URL: Homepage, https://github.com/yourusername/dicom-tools-mcp
Project-URL: Repository, https://github.com/yourusername/dicom-tools-mcp
Project-URL: Issues, https://github.com/yourusername/dicom-tools-mcp/issues
Author-email: jiancong Zhang <1316795665@qq.com>
License: MIT
License-File: LICENSE
Keywords: dicom,mcp,medical-imaging,model-context-protocol,orthanc
Classifier: Development Status :: 3 - Alpha
Classifier: Intended Audience :: Developers
Classifier: Intended Audience :: Healthcare Industry
Classifier: License :: OSI Approved :: MIT License
Classifier: Programming Language :: Python :: 3.10
Classifier: Programming Language :: Python :: 3.11
Classifier: Programming Language :: Python :: 3.12
Classifier: Topic :: Scientific/Engineering :: Medical Science Apps.
Requires-Python: >=3.10
Requires-Dist: mcp>=0.9.0
Requires-Dist: pydantic>=2.0.0
Requires-Dist: pydicom>=2.4.0
Requires-Dist: pyorthanc
Requires-Dist: requests>=2.31.0
Requires-Dist: tqdm>=4.66.0
